rich_objects/__init__.py
rich_objects/console.py
rich_objects/constants.py
rich_objects/display.py
rich_objects/enums.py
rich_objects/rich_table.py
rich_objects/table_config.py
rich_objects-0.2.1.dist-info/METADATA
rich_objects-0.2.1.dist-info/WHEEL
rich_objects-0.2.1.dist-info/licenses/LICENSE
rich_objects-0.2.1.dist-info/RECORD
